expected_levenshtein/__init__.py
expected_levenshtein/fit.py
expected_levenshtein/sample.py
expected_levenshtein/version.py
expected_levenshtein/models/__init__.py
expected_levenshtein/models/k20_n6k_r10k_models.json
expected_levenshtein/tests/__init__.py
expected_levenshtein/tests/test_fitting.py
expected_levenshtein/tests/test_sampling.py
expected_levenshtein-0.1.2.dist-info/LICENSE.txt
expected_levenshtein-0.1.2.dist-info/METADATA
expected_levenshtein-0.1.2.dist-info/WHEEL
expected_levenshtein-0.1.2.dist-info/top_level.txt
expected_levenshtein-0.1.2.dist-info/RECORD
