Metadata-Version: 2.1
Name: expected-levenshtein
Version: 0.1.2
Summary: 
Home-page: https://github.com/nickmachnik/expected-levenshtein.git
Author: Nick Noel Machnik
Author-email: nick.machnik@gmail.com
License: UNKNOWN
Platform: UNKNOWN
Classifier: Programming Language :: Python :: 3
Classifier: License :: OSI Approved :: MIT License
Classifier: Operating System :: OS Independent
Requires-Dist: numpy (>=1.8.0)
Requires-Dist: numba
Requires-Dist: importlib-resources
